tree_source_localization/EdgeDistribution.py
tree_source_localization/MGFAugment.py
tree_source_localization/MGFFunctions.py
tree_source_localization/Search.py
tree_source_localization/Tree.py
tree_source_localization/__init__.py
tree_source_localization/cli.py
tree_source_localization-1.0.4.dist-info/licenses/LICENSE
tree_source_localization-1.0.4.dist-info/METADATA
tree_source_localization-1.0.4.dist-info/WHEEL
tree_source_localization-1.0.4.dist-info/entry_points.txt
tree_source_localization-1.0.4.dist-info/top_level.txt
tree_source_localization-1.0.4.dist-info/RECORD
