Metadata-Version: 2.4
Name: tree-source-localization
Version: 1.0.4
Summary: A package for source localization on tree infection networks
Author-email: Devlin Costello <devlin.costello@colorado.edu>
License-Expression: GPL-3.0-or-later
Requires-Python: >=3.8
License-File: LICENSE
Requires-Dist: numpy
Requires-Dist: scipy
Dynamic: license-file
